promuet/__init__.py
promuet/ai_client.py
promuet/app_flow.py
promuet/match_items.py
promuet/prompt_flow.py
promuet/prompt_message.py
promuet-0.3.3.dist-info/METADATA
promuet-0.3.3.dist-info/WHEEL
promuet-0.3.3.dist-info/licenses/LICENSE.txt
promuet-0.3.3.dist-info/RECORD
