Metadata-Version: 2.4
Name: promuet
Version: 0.3.3
Summary: A simple yet powerful prompt templating engine
Project-URL: Documentation, https://github.com/MatthewScholefield/promuet#readme
Project-URL: Issues, https://github.com/MatthewScholefield/promuet/issues
Project-URL: Source, https://github.com/MatthewScholefield/promuet
Author-email: "Matthew D. Scholefield" <matthew331199@gmail.com>
License-Expression: MIT
License-File: LICENSE.txt
Classifier: Development Status :: 4 - Beta
Classifier: Programming Language :: Python
Classifier: Programming Language :: Python :: 3.10
Classifier: Programming Language :: Python :: 3.11
Classifier: Programming Language :: Python :: 3.12
Classifier: Programming Language :: Python :: Implementation :: CPython
Classifier: Programming Language :: Python :: Implementation :: PyPy
Requires-Python: >=3.10
Requires-Dist: loguru
Requires-Dist: openai
Requires-Dist: pydantic
